girok/__init__.py
girok/api/auth.py
girok/api/category.py
girok/api/entity.py
girok/api/task.py
girok/api_client.py
girok/calendar_cli/__init__.py
girok/calendar_cli/calendar_app.py
girok/calendar_cli/calendar_container.py
girok/calendar_cli/calendar_main.css
girok/calendar_cli/calendar_main.py
girok/calendar_cli/entity.py
girok/calendar_cli/sidebar.py
girok/calendar_cli/textual_demo_2023-03-11T22_49_21_681307.svg
girok/calendar_cli/utils.py
girok/commands/auth/command.py
girok/commands/calendar/command.py
girok/commands/category/command.py
girok/commands/category/util.py
girok/commands/task/callbacks.py
girok/commands/task/command.py
girok/commands/task/display.py
girok/commands/task/entity.py
girok/commands/task/utils.py
girok/config/auth_handler.py
girok/constants.py
girok/girok.py
girok/utils/display.py
girok/utils/json_utils.py
girok/utils/time.py
girok-0.3.0.dist-info/LICENSE
girok-0.3.0.dist-info/METADATA
girok-0.3.0.dist-info/WHEEL
girok-0.3.0.dist-info/entry_points.txt
girok-0.3.0.dist-info/RECORD
