Metadata-Version: 2.3
Name: girok
Version: 0.3.0
Summary: Moved resources directory from girok directory to root directory
Author: Jason Lee
Author-email: changjin9792@gmail.com
Requires-Python: >=3.9,<4.0
Classifier: Programming Language :: Python :: 3
Classifier: Programming Language :: Python :: 3.9
Classifier: Programming Language :: Python :: 3.10
Classifier: Programming Language :: Python :: 3.11
Classifier: Programming Language :: Python :: 3.12
Classifier: Programming Language :: Python :: 3.13
Requires-Dist: requests (>=2.31.0,<3.0.0)
Requires-Dist: textual (>=0.48.1,<0.49.0)
Requires-Dist: typer[all] (>=0.9.0,<0.10.0)
